bitmapist4/__init__.py
bitmapist4/__version__.py
bitmapist4/cohort.py
bitmapist4/core.py
bitmapist4/events.py
bitmapist4/sample.py
bitmapist4-4.0.dist-info/AUTHORS
bitmapist4-4.0.dist-info/METADATA
bitmapist4-4.0.dist-info/WHEEL
bitmapist4-4.0.dist-info/top_level.txt
bitmapist4-4.0.dist-info/RECORD
