Metadata-Version: 2.1
Name: bitmapist4
Version: 4.0
Summary: Powerful analytics library using Redis bitmaps
Home-page: https://github.com/Doist/bitmapist4
Author: Doist Team
Author-email: dev@doist.com
License: BSD
Keywords: redis bitmap analytics bitmaps realtime cohort
Platform: Any
Classifier: Development Status :: 5 - Production/Stable
Classifier: Intended Audience :: Developers
Classifier: License :: OSI Approved :: BSD License
Classifier: Operating System :: OS Independent
Classifier: Programming Language :: Python
Classifier: Programming Language :: Python :: 2
Classifier: Programming Language :: Python :: 2.7
Classifier: Programming Language :: Python :: 3
Classifier: Programming Language :: Python :: 3.4
Classifier: Programming Language :: Python :: 3.5
Classifier: Programming Language :: Python :: 3.6
Classifier: Topic :: Software Development :: Libraries :: Python Modules
Requires-Dist: redis (>=2.10)
Requires-Dist: future (>=0.14)
